McFit/McFit.py
McFit/__init__.py
Squires_McFit-0.1.dist-info/METADATA
Squires_McFit-0.1.dist-info/WHEEL
Squires_McFit-0.1.dist-info/top_level.txt
Squires_McFit-0.1.dist-info/RECORD
