Metadata-Version: 2.1
Name: Squires-McFit
Version: 0.1
Summary: Markov Chain Monte Carlo curve fitting
Author: Andrés Cook
Author-email: <andcook5@gmail.com>
Keywords: python,fitting
Classifier: Development Status :: 3 - Alpha
Classifier: Intended Audience :: Education
Classifier: Programming Language :: Python :: 2
Classifier: Programming Language :: Python :: 3
Classifier: Operating System :: MacOS :: MacOS X
Classifier: Operating System :: Microsoft :: Windows
Requires-Dist: numpy
Requires-Dist: matplotlib.pyplot
Requires-Dist: corner
Requires-Dist: typing
Requires-Dist: progress.bar
